django_dfk-0.0.10.dist-info/top_level.txt
django_dfk-0.0.10.dist-info/metadata.json
django_dfk-0.0.10.dist-info/RECORD
django_dfk-0.0.10.dist-info/METADATA
django_dfk-0.0.10.dist-info/DESCRIPTION.rst
django_dfk-0.0.10.dist-info/WHEEL
dfk/tests.py
dfk/test_settings.py
dfk/models.py
dfk/__init__.py
