Metadata-Version: 2.0
Name: django-dfk
Version: 0.0.10
Summary: Deferred foreign keys for Django
Home-page: UNKNOWN
Author: Dan Fairs
Author-email: dan@fezconsulting.com
License: BSD
Platform: UNKNOWN
Classifier: Programming Language :: Python
Classifier: Programming Language :: Python :: 2
Classifier: Programming Language :: Python :: 2.6
Classifier: Programming Language :: Python :: 2.7
Classifier: Programming Language :: Python :: 3
Classifier: Programming Language :: Python :: 3.2
Classifier: Programming Language :: Python :: 3.3
Classifier: Topic :: Software Development :: Libraries :: Python Modules
Classifier: Framework :: Django
Classifier: Development Status :: 3 - Alpha
Classifier: License :: OSI Approved :: BSD License
Requires-Dist: django (>=1.3,<1.8)
